sikuli/__init__.py
sikuli/find.py
sikuli/run.py
sikuli/version.py
sikuli/script/__init__.py
sikuli/script/app.py
sikuli/script/env.py
sikuli/script/exc.py
sikuli/script/finder.py
sikuli/script/image.py
sikuli/script/key.py
sikuli/script/location.py
sikuli/script/match.py
sikuli/script/pattern.py
sikuli/script/rectangle.py
sikuli/script/region.py
sikuli/script/robot.py
sikuli/script/screen.py
sikuli/script/settings.py
sikuli/script/sikulpy.py
sikulpy-0.0.dist-info/LICENSE.txt
sikulpy-0.0.dist-info/METADATA
sikulpy-0.0.dist-info/WHEEL
sikulpy-0.0.dist-info/entry_points.txt
sikulpy-0.0.dist-info/top_level.txt
sikulpy-0.0.dist-info/RECORD
