Metadata-Version: 2.1
Name: sikulpy
Version: 0.0
Summary: An implementation of Sikuli for CPython
Home-page: https://github.com/shish/sikulpy
Author: Shish
Author-email: webmaster@shishnet.org
License: UNKNOWN
Platform: UNKNOWN
Classifier: Development Status :: 4 - Beta
Classifier: Environment :: Console
Classifier: Intended Audience :: Developers
Classifier: Programming Language :: Python :: 3.7
Classifier: Topic :: Utilities
Requires-Dist: autopy3
Requires-Dist: pillow
Requires-Dist: numpy
Requires-Dist: mss
Requires-Dist: pyperclip
Requires-Dist: opencv-python
